pupil_labs/marker_mapper/__init__.py
pupil_labs/marker_mapper/py.typed
pupil_labs/marker_mapper/surface.py
pupil_labs/marker_mapper/utils.py
pupil_labs_marker_mapper-1.0.0.dist-info/METADATA
pupil_labs_marker_mapper-1.0.0.dist-info/WHEEL
pupil_labs_marker_mapper-1.0.0.dist-info/licenses/LICENSE
pupil_labs_marker_mapper-1.0.0.dist-info/RECORD
