Metadata-Version: 2.4
Name: pupil-labs-marker-mapper
Version: 1.0.0
Summary: Marker Mapper
Project-URL: Homepage, https://pupil-labs.github.io/pl-marker-mapper
Project-URL: Documentation, https://pupil-labs.github.io/pl-marker-mapper
Project-URL: Repository, https://github.com/pupil-labs/pl-marker-mapper
Project-URL: Issues, https://github.com/pupil-labs/pl-marker-mapper/issues
Author-email: Pupil Labs GmbH <info@pupil-labs.com>
License: MIT
License-File: LICENSE
Classifier: Intended Audience :: Developers
Classifier: Programming Language :: Python
Classifier: Programming Language :: Python :: 3
Classifier: Programming Language :: Python :: 3.10
Classifier: Programming Language :: Python :: 3.11
Classifier: Programming Language :: Python :: 3.12
Classifier: Programming Language :: Python :: 3.13
Classifier: Topic :: Software Development :: Libraries :: Python Modules
Requires-Python: <4.0,>=3.10
Requires-Dist: numpy
Requires-Dist: opencv-python>=4.11.0.86
Requires-Dist: pupil-apriltags>=1.0.4.post11
Requires-Dist: pupil-labs-camera
Requires-Dist: pupil-labs-neon-recording>=1.0.3
Provides-Extra: examples
Requires-Dist: opencv-python>=4.11.0.86; extra == 'examples'
Requires-Dist: pupil-labs-realtime-api>=1.6.2; extra == 'examples'
Requires-Dist: pyside6>=6.9.1; extra == 'examples'
